[
  {"county_code": "63000", "county_name_zh": "臺北市", "county_name_en": "Taipei City"},
  {"county_code": "65000", "county_name_zh": "新北市", "county_name_en": "New Taipei City"},
  {"county_code": "68000", "county_name_zh": "桃園市", "county_name_en": "Taoyuan City"},
  {"county_code": "10002", "county_name_zh": "宜蘭縣", "county_name_en": "Yilan County"},
  {"county_code": "10004", "county_name_zh": "新竹縣", "county_name_en": "Hsinchu County"},
  {"county_code": "10018", "county_name_zh": "新竹市", "county_name_en": "Hsinchu City"},
  {"county_code": "10005", "county_name_zh": "苗栗縣", "county_name_en": "Miaoli County"},
  {"county_code": "66000", "county_name_zh": "臺中市", "county_name_en": "Taichung City"},
  {"county_code": "10007", "county_name_zh": "彰化縣", "county_name_en": "Changhua County"},
  {"county_code": "10008", "county_name_zh": "南投縣", "county_name_en": "Nantou County"},
  {"county_code": "10009", "county_name_zh": "雲林縣", "county_name_en": "Yunlin County"},
  {"county_code": "10010", "county_name_zh": "嘉義縣", "county_name_en": "Chiayi County"},
  {"county_code": "10020", "county_name_zh": "嘉義市", "county_name_en": "Chiayi City"},
  {"county_code": "67000", "county_name_zh": "臺南市", "county_name_en": "Tainan City"},
  {"county_code": "64000", "county_name_zh": "高雄市", "county_name_en": "Kaohsiung City"},
  {"county_code": "10013", "county_name_zh": "屏東縣", "county_name_en": "Pingtung County"},
  {"county_code": "10014", "county_name_zh": "臺東縣", "county_name_en": "Taitung County"},
  {"county_code": "10015", "county_name_zh": "花蓮縣", "county_name_en": "Hualien County"},
  {"county_code": "10016", "county_name_zh": "澎湖縣", "county_name_en": "Penghu County"},
  {"county_code": "09020", "county_name_zh": "金門縣", "county_name_en": "Kinmen County"},
  {"county_code": "09007", "county_name_zh": "連江縣", "county_name_en": "Lienchiang County"},
  {"county_code": "10017", "county_name_zh": "基隆市", "county_name_en": "Keelung City"}
]
